MANIFEST.in
README.md
setup.py
csv2sqllike/PseudoSQLFromCSV.py
csv2sqllike/Transfer2SQLDB.py
csv2sqllike/__init__.py
csv2sqllike/info.py
csv2sqllike.egg-info/PKG-INFO
csv2sqllike.egg-info/SOURCES.txt
csv2sqllike.egg-info/dependency_links.txt
csv2sqllike.egg-info/requires.txt
csv2sqllike.egg-info/top_level.txt
samples/examples.ipynb
samples/sample.csv
samples/.ipynb_checkpoints/sample-checkpoint.csv