Metadata-Version: 2.1
Name: csv2sqllike
Version: 1.5.2
Summary: Python functions for data analysis using python native container. Load data from csv files and deal with data like sql.
Home-page: https://github.com/hoosiki/csv2sqlLike
Author: Junsang Park
Author-email: publichey@gmail.com
License: BSD
Download-URL: https://github.com/hoosiki/csv2sqlLike/blob/master/dist/csv2sqllike-1.5.2.tar.gz
Platform: UNKNOWN
